odoo/addons/uom_unece/README.rst
odoo/addons/uom_unece/__init__.py
odoo/addons/uom_unece/__manifest__.py
odoo/addons/uom_unece/data/unece.xml
odoo/addons/uom_unece/i18n/fr.po
odoo/addons/uom_unece/i18n/it.po
odoo/addons/uom_unece/i18n/pt.po
odoo/addons/uom_unece/i18n/tr.po
odoo/addons/uom_unece/i18n/uom_unece.pot
odoo/addons/uom_unece/models/__init__.py
odoo/addons/uom_unece/models/uom_uom.py
odoo/addons/uom_unece/readme/CONFIGURE.rst
odoo/addons/uom_unece/readme/CONTRIBUTORS.rst
odoo/addons/uom_unece/readme/DESCRIPTION.rst
odoo/addons/uom_unece/static/description/icon.png
odoo/addons/uom_unece/static/description/index.html
odoo/addons/uom_unece/views/product_uom.xml
odoo12_addon_uom_unece-12.0.1.1.0.99.dev16.dist-info/METADATA
odoo12_addon_uom_unece-12.0.1.1.0.99.dev16.dist-info/WHEEL
odoo12_addon_uom_unece-12.0.1.1.0.99.dev16.dist-info/top_level.txt
odoo12_addon_uom_unece-12.0.1.1.0.99.dev16.dist-info/RECORD
